[
    {
      "id": "84963338-c7db-435d-ab5d-3e5b51c10746",
      "characteristic_name": "Hair",
      "choices": [
        "Neat and Clean",
        "Presentable",
        "Acceptable",
        "Needs Attention",
        "Could Be Cleaner"
      ]
    },
    {
      "id": "da0839a1-165c-49b8-b37e-90ba5c5e874a",
      "characteristic_name": "Mouth",
      "choices": [
        "Pleasant Breath",
        "Clean Teeth",
        "Needs Better Hygiene",
        "Could Be Fresher"
      ]
    },
    {
      "id": "f039051f-a474-4222-bac5-dabdb63cc705",
      "characteristic_name": "Body Odor",
      "choices": [
        "Fresh",
        "Good",
        "No Odor",
        "Could Be Better",
        "Needs Improvements"
      ]
    }
  ]
  